odoo/addons/cms_info/CHANGES.rst
odoo/addons/cms_info/README.rst
odoo/addons/cms_info/__init__.py
odoo/addons/cms_info/__manifest__.py
odoo/addons/cms_info/i18n/cms_info.pot
odoo/addons/cms_info/models/__init__.py
odoo/addons/cms_info/models/website_mixin.py
odoo/addons/cms_info/static/description/icon.png
odoo/addons/cms_info/tests/__init__.py
odoo/addons/cms_info/tests/fake_models.py
odoo/addons/cms_info/tests/test_info_mixin.py
odoo11_addon_cms_info-11.0.1.0.2.dist-info/METADATA
odoo11_addon_cms_info-11.0.1.0.2.dist-info/WHEEL
odoo11_addon_cms_info-11.0.1.0.2.dist-info/top_level.txt
odoo11_addon_cms_info-11.0.1.0.2.dist-info/RECORD
